.twphotos
CHANGELOG.rst
LICENSE
MANIFEST.in
README.rst
setup.py
testdata/statuses.json
twitter_photos.egg-info/PKG-INFO
twitter_photos.egg-info/SOURCES.txt
twitter_photos.egg-info/dependency_links.txt
twitter_photos.egg-info/entry_points.txt
twitter_photos.egg-info/not-zip-safe
twitter_photos.egg-info/requires.txt
twitter_photos.egg-info/top_level.txt
twphotos/__init__.py
twphotos/cli.py
twphotos/increment.py
twphotos/parallel.py
twphotos/photos.py
twphotos/settings.py
twphotos/tests.py
twphotos/utils.py