Metadata-Version: 1.1
Name: twitter-photos
Version: 0.2.0
Summary: Command-line tool to get photos from Twitter accounts.
Home-page: https://github.com/shichao-an/twitter-photos
Author: Shichao An
Author-email: shichao.an@nyu.edu
License: BSD
Keywords: twitter photos
Platform: UNKNOWN
Classifier: Environment :: Console
Classifier: License :: OSI Approved :: BSD License
Classifier: Programming Language :: Python
Classifier: Programming Language :: Python :: 2
